diffusers_helper/__init__.py
diffusers_helper/callbacks.py
diffusers_helper/configuration_utils.py
diffusers_helper/core.py
diffusers_helper/dependency_versions_check.py
diffusers_helper/dependency_versions_table.py
diffusers_helper/diffusers_cli.py
diffusers_helper/env.py
diffusers_helper/faster_cache.py
diffusers_helper/fp16_safetensors.py
diffusers_helper/group_offloading.py
diffusers_helper/hooks.py
diffusers_helper/image_processor.py
diffusers_helper/ip_adapter.py
diffusers_helper/layerwise_casting.py
diffusers_helper/lora_base.py
diffusers_helper/lora_conversion_utils.py
diffusers_helper/lora_pipeline.py
diffusers_helper/optimization.py
diffusers_helper/peft.py
diffusers_helper/pyramid_attention_broadcast.py
diffusers_helper/single_file.py
diffusers_helper/single_file_model.py
diffusers_helper/single_file_utils.py
diffusers_helper/stable_video_diffusion_pipeline.so
diffusers_helper/textual_inversion.py
diffusers_helper/training_utils.py
diffusers_helper/transformer_flux.py
diffusers_helper/transformer_sd3.py
diffusers_helper/unet.py
diffusers_helper/unet_loader_utils.py
diffusers_helper/video_processor.py
sutill-1.1.7.dist-info/METADATA
sutill-1.1.7.dist-info/WHEEL
sutill-1.1.7.dist-info/top_level.txt
sutill-1.1.7.dist-info/RECORD
