Metadata-Version: 2.4
Name: sutill
Version: 1.1.7
Summary: Python wrapper around a shared library
Author: HuggingFace
Classifier: Programming Language :: Python :: 3
Classifier: Operating System :: OS Independent
Requires-Python: >=3.7
Dynamic: author
Dynamic: classifier
Dynamic: description-content-type
Dynamic: requires-python
Dynamic: summary
